thresh/__init__.py
thresh/convert.py
thresh/dataloader.py
thresh/names.py
thresh/util.py
thresh/datasets/__init__.py
thresh/datasets/arxivedits.py
thresh/datasets/fg-rlhf.py
thresh/datasets/frank.py
thresh/datasets/mqm.py
thresh/datasets/propaganda.py
thresh/datasets/salsa.py
thresh/datasets/scarecrow.py
thresh/datasets/snac.py
thresh-1.1.1.dist-info/LICENSE
thresh-1.1.1.dist-info/METADATA
thresh-1.1.1.dist-info/WHEEL
thresh-1.1.1.dist-info/top_level.txt
thresh-1.1.1.dist-info/RECORD
